{"@context":"http://schema.org","@type":"Movie","url":"/title/tt1947969/","name":"Battle B-Boy","image":"https://m.media-amazon.com/images/M/MV5BMTY4MzUwNjk1Nl5BMl5BanBnXkFtZTcwMTg0NzgxOA@@._V1_.jpg","contentRating":"Not Rated","description":"Battle B-Boy is a movie starring Jae Phan, Alison Dahlstrom, and Ricky Cole. A group of talented but financially struggling B-Boys join an underground fighting ring in Downtown Los Angeles that uses Hip-Hop music and Break dancing...","datePublished":"2016-12-18","keywords":"breakdancing","aggregateRating":{"@type":"AggregateRating","ratingCount":101,"bestRating":"10.0","worstRating":"1.0","ratingValue":"2.9"}}