{"@context":"http://schema.org","@type":"Movie","url":"/title/tt1986097/","name":"Payne \u0026 Redemption","image":"https://m.media-amazon.com/images/M/MV5BMThiZTljMWUtZDNjNy00MTExLTg1Y2ItMjU0YzliNjc4OGY2XkEyXkFqcGdeQXVyMzYzNzc1NjY@._V1_.jpg","contentRating":"","description":"Payne \u0026 Redemption is a movie starring Kylie Cushman, John Mangan, and David Soul. The story revolves around a guilt riddent NYC detective turned DEA agent. When his family gets murdered by henchmen of drug dealer cum mafia don.","datePublished":"2018-10-04","keywords":"detective,new york,revenge,anti hero,hard boiled","aggregateRating":{"@type":"AggregateRating","ratingCount":7,"bestRating":"10.0","worstRating":"1.0","ratingValue":"8.0"}}