{"@context":"http://schema.org","@type":"Movie","url":"/title/tt2520046/","name":"Madraza","image":"https://m.media-amazon.com/images/M/MV5BMGQyZjRiYmQtMzhmMC00MTI2LWJlODAtMWYzMmM5NWQ2NzIxXkEyXkFqcGdeQXVyMzcxNzUxNzU@._V1_.jpg","contentRating":"","description":"Madraza is a movie starring Loren Acuña, Gustavo Garzón, and Sofía Gala. A humble housewife becomes an assassin for money, gaining self-confidence and rebuilding her life.","datePublished":"2017-05-25","keywords":"housewife,assassin,fight,choke,gun","aggregateRating":{"@type":"AggregateRating","ratingCount":114,"bestRating":"10.0","worstRating":"1.0","ratingValue":"5.9"}}