{"@context":"http://schema.org","@type":"Movie","url":"/title/tt3231530/","name":"The Journey to Aresmore","image":"https://m.media-amazon.com/images/M/MV5BNTZiMWY0YmEtNjc5Zi00MDAyLTkwYjQtOGZmOTRlZGNlYzI2XkEyXkFqcGdeQXVyNDUxNjc5NjY@._V1_.jpg","contentRating":"","description":"The Journey to Aresmore is a movie starring Joshua Copeland and Adam Starks. The Journey to Aresmore follows the story of two 17 year old boys (Peter Townsend and Jack Cunningham) mysteriously taken into another world Known as...","datePublished":"2016-01-01","keywords":"sword and sorcery","aggregateRating":{"@type":"","ratingCount":0,"bestRating":"","worstRating":"","ratingValue":""}}