{"@context":"http://schema.org","@type":"Movie","url":"/title/tt4954660/","name":"Meitantei Conan: Junkoku no naitomea","image":"https://m.media-amazon.com/images/M/MV5BYzQ0ZDJjZmUtNDQwNS00ZTZkLTgzYmEtNDdmZDgzNmE1MDUwXkEyXkFqcGdeQXVyMjQ5NjMxNDA@._V1_.jpg","contentRating":"","description":"Meitantei Conan: Junkoku no naitomea is a movie starring Kappei Yamaguchi, Rikiya Koyama, and Minami Takayama. A spy infiltrated the Japanese National Police Agency, retrieving secret files of Britain's MI6, Germany's BND and...","datePublished":"2016-04-16","keywords":"anime,based on manga,twentieth part,sequel","aggregateRating":{"@type":"AggregateRating","ratingCount":1134,"bestRating":"10.0","worstRating":"1.0","ratingValue":"7.0"}}