{"@context":"http://schema.org","@type":"Movie","url":"/title/tt5255524/","name":"Traded","image":"https://m.media-amazon.com/images/M/MV5BZWZmYWEzN2YtZjNlMC00M2U4LWE3ZjUtNjkzM2Q4OWZiZDNkXkEyXkFqcGdeQXVyMzY0MzA3NTg@._V1_.jpg","contentRating":"Not Rated","description":"Traded is a movie starring Kris Kristofferson, Trace Adkins, and Michael Paré. In the 1880s western \"Traded\", a father must leave his ranch for Dodge City to save his daughter from an old enemy, putting his reputation as the fastest...","datePublished":"2016-06-10","keywords":"harvey girl,1880s,pie,honey,piano","aggregateRating":{"@type":"AggregateRating","ratingCount":2462,"bestRating":"10.0","worstRating":"1.0","ratingValue":"5.1"}}