{"@context":"http://schema.org","@type":"Movie","url":"/title/tt5334856/","name":"Nun Smack","image":"https://m.media-amazon.com/images/M/MV5BYWRmZTIyZjMtNDc0ZC00MzZjLWJmZjktYTc5YmJiMWQ1NmRiXkEyXkFqcGdeQXVyNDIwMTQ0NDU@._V1_.jpg","contentRating":"","description":"Nun Smack is a movie starring Rob Merritt, Brad Quinn, and Shawn Beta. Two petty crooks seek refuge in a church after a drug-deal-gone-wrong - and find that their troubles are just beginning.","datePublished":"2016-09-25","keywords":"church,cocaine,nun,car chase,crooked cop","aggregateRating":{"@type":"AggregateRating","ratingCount":6,"bestRating":"10.0","worstRating":"1.0","ratingValue":"5.3"}}