{"@context":"http://schema.org","@type":"Movie","url":"/title/tt6383652/","name":"Daud Pakad","image":"https://m.media-amazon.com/images/M/MV5BNTg2YTYzN2MtY2ZmNi00ZjRkLWE4Y2EtMGUzZDJiMjNjYzVmL2ltYWdlL2ltYWdlXkEyXkFqcGdeQXVyNTcxMjc4NDY@._V1_.jpg","contentRating":"","description":"Daud Pakad is a movie starring Prem Gadhavi, Jayesh More, and Hemin Trivedi. After a party, on their way to Baroda, 5 friends experience their worst nightmare in the form of police and gangsters.","datePublished":"2019-07-26","keywords":"gujarati film","aggregateRating":{"@type":"","ratingCount":0,"bestRating":"","worstRating":"","ratingValue":""}}