{"@context":"http://schema.org","@type":"Movie","url":"/title/tt8377564/","name":"The Bachelor 3","image":"https://m.media-amazon.com/images/M/MV5BMTdmYzU0YzktNTZlNy00NDY0LWI4YzUtOTNjYTRiZTZlNTgzXkEyXkFqcGdeQXVyMjMyNzkwMzk@._V1_.jpg","contentRating":"","description":"The Bachelor 3 is a movie starring Yannis Tsimitselis, Thanasis Viskadourakis, and Nikos Vourliotis. Jimmy is getting married and he gathers his buddies for the legendary bachelor. All is surprisingly normal this time and the...","datePublished":"2018-12-25","keywords":"","aggregateRating":{"@type":"AggregateRating","ratingCount":186,"bestRating":"10.0","worstRating":"1.0","ratingValue":"4.5"}}