{"@context":"http://schema.org","@type":"Movie","url":"/title/tt4573096/","name":"Mac Daddy's Vegas Adventure","image":"https://m.media-amazon.com/images/M/MV5BMTA4MjI5OTY4OTdeQTJeQWpwZ15BbWU4MDI2ODIzNzgx._V1_.jpg","contentRating":"","description":"Mac Daddy's Vegas Adventure is a movie starring Mac Jay, Franco Rossi, and Madeleine Wade. After Mac Daddy decides to quit being an international ladies man, two of his best pupils (Diego and Damon), whom have been trained by him in...","datePublished":"2017-06-17","keywords":"italian mafia","aggregateRating":{"@type":"","ratingCount":0,"bestRating":"","worstRating":"","ratingValue":""}}