{"@context":"http://schema.org","@type":"Movie","url":"/title/tt4796634/","name":"Selfie 69","image":"https://m.media-amazon.com/images/M/MV5BYTVjYjIwOTctZDI2Yi00NDk2LTgxNGYtZjY1MjNhNTRmYzU3XkEyXkFqcGdeQXVyNDgxMDU4NTU@._V1_.jpg","contentRating":"","description":"Selfie 69 is a movie starring Silvia Busuioc, Bogdan Alexandru, and Raluca Aprodu. Your best friends are also the friends who'll make you do the stupidest things. After parting hardcore, Roxi, Yasmine and Ana meet in a bet that will...","datePublished":"2016-09-16","keywords":"f rated","aggregateRating":{"@type":"AggregateRating","ratingCount":942,"bestRating":"10.0","worstRating":"1.0","ratingValue":"6.9"}}