{"@context":"http://schema.org","@type":"Movie","url":"/title/tt4717208/","name":"Cops and Robbers","image":"https://m.media-amazon.com/images/M/MV5BZGEwYjIxMDAtZTUyNi00YTgxLWE5NGMtN2M0ODhiYzExOTZiXkEyXkFqcGdeQXVyOTg4MDYyNw@@._V1_.jpg","contentRating":"R","description":"Cops and Robbers is a movie starring Michael Jai White, Quinton 'Rampage' Jackson, and Tom Berenger. A strung out hostage negotiator plays a dangerous game of cat and mouse with a cornered bank robber who is hell bent on getting out...","datePublished":"2017-12-12","keywords":"","aggregateRating":{"@type":"AggregateRating","ratingCount":298,"bestRating":"10.0","worstRating":"1.0","ratingValue":"3.9"}}