{"@context":"http://schema.org","@type":"Movie","url":"/title/tt5191164/","name":"Corruption II","image":"https://m.media-amazon.com/images/M/MV5BMjE4MzE0NDA0N15BMl5BanBnXkFtZTgwMjY0OTAzNzE@._V1_.jpg","contentRating":"PG-13","description":"Corruption II is a movie starring Michael L. Knight, Maria Pazouros, and Karl Greenwood. Gritty independent action/thriller set in Manchester, UK starring Michael L. Knight.","datePublished":"","keywords":"deception,knight,manchester,life,new","aggregateRating":{"@type":"AggregateRating","ratingCount":8,"bestRating":"10.0","worstRating":"1.0","ratingValue":"5.8"}}