{"@context":"http://schema.org","@type":"Movie","url":"/title/tt5460276/","name":"Kaabil","image":"https://m.media-amazon.com/images/M/MV5BMWJkMjJiNzMtNzhmOC00MjQ3LTg5MmEtMTRkMTg1ZjQ2ZmM1L2ltYWdlL2ltYWdlXkEyXkFqcGdeQXVyNDkxMzY0Mjk@._V1_.jpg","contentRating":"Not Rated","description":"Kaabil is a movie starring Hrithik Roshan, Yami Gautam, and Ronit Roy. A blind man seeks revenge against a corrupt politician and his brother after his wife is raped and killed.","datePublished":"2017-01-25","keywords":"blind man,murder,blind hero,loss of loved one,love","aggregateRating":{"@type":"AggregateRating","ratingCount":21996,"bestRating":"10.0","worstRating":"1.0","ratingValue":"7.1"}}