{"@context":"http://schema.org","@type":"Movie","url":"/title/tt6129302/","name":"Bhavesh Joshi Superhero","image":"https://m.media-amazon.com/images/M/MV5BOWYxMGM5NGUtYjE4Mi00NjQ2LTllYjUtNTMyNTdjZGIxZjcxXkEyXkFqcGdeQXVyNzkxOTEyMjI@._V1_.jpg","contentRating":"Not Rated","description":"Bhavesh Joshi Superhero is a movie starring Harsh Varrdhan Kapoor, Priyanshu Painyuli, and Ashish Verma. The origin story of Bhavesh Joshi, an Indian superhero, who sets out to fulfill his slain friend's wish to clean and reform the...","datePublished":"2018-06-01","keywords":"vigilante,friendship,violence,death,killed with a hammer","aggregateRating":{"@type":"AggregateRating","ratingCount":4127,"bestRating":"10.0","worstRating":"1.0","ratingValue":"7.6"}}