{"@context":"http://schema.org","@type":"Movie","url":"/title/tt6936384/","name":"Dedunu Akase","image":"https://m.media-amazon.com/images/M/MV5BN2NjNjQyNDEtZTI3NC00MGM3LTg5M2YtZWVkZmMwYjA5YmYyXkEyXkFqcGdeQXVyNDMwOTc5MDg@._V1_.jpg","contentRating":"","description":"Dedunu Akase is a movie starring Sriyani Amarasena, Dasun de Silva, and Dinindu Ekanayake. A colorful and musical love triangle which takes a twisted end. Spans for a period of about a decade starting from youthful college times to...","datePublished":"2017-10-12","keywords":"","aggregateRating":{"@type":"AggregateRating","ratingCount":124,"bestRating":"10.0","worstRating":"1.0","ratingValue":"7.5"}}